atlasai/toolkit/__init__.py
atlasai/toolkit/api.py
atlasai/toolkit/constants.py
atlasai/toolkit/dataset.py
atlasai/toolkit/fabric.py
atlasai/toolkit/feature.py
atlasai/toolkit/init.py
atlasai/toolkit/login.py
atlasai/toolkit/model.py
atlasai/toolkit/output.py
atlasai/toolkit/requests.py
atlasai/toolkit/utils.py
atlasai/toolkit/workflows.py
atlasai_dstoolkit_client-0.0.21.dist-info/LICENSE.txt
atlasai_dstoolkit_client-0.0.21.dist-info/METADATA
atlasai_dstoolkit_client-0.0.21.dist-info/WHEEL
atlasai_dstoolkit_client-0.0.21.dist-info/top_level.txt
atlasai_dstoolkit_client-0.0.21.dist-info/RECORD
